<annotation>
	<folder>sunspot</folder>
	<filename>20101212_000000_SDO_HMI_Ic_512.jpg</filename>
	<path>D:\kasi\Research\2020\2020_ObjectDetection\data\sunspot\20101212_000000_SDO_HMI_Ic_512.jpg</path>
	<source>
		<database>Unknown</database>
	</source>
	<size>
		<width>512</width>
		<height>512</height>
		<depth>3</depth>
	</size>
	<segmented>0</segmented>
	<object>
		<name>sunspot</name>
		<pose>Unspecified</pose>
		<truncated>0</truncated>
		<difficult>0</difficult>
		<bndbox>
			<xmin>325</xmin>
			<ymin>180</ymin>
			<xmax>351</xmax>
			<ymax>206</ymax>
		</bndbox>
	</object>
	<object>
		<name>sunspot</name>
		<pose>Unspecified</pose>
		<truncated>0</truncated>
		<difficult>0</difficult>
		<bndbox>
			<xmin>390</xmin>
			<ymin>116</ymin>
			<xmax>419</xmax>
			<ymax>145</ymax>
		</bndbox>
	</object>
</annotation>
