<annotation>
	<folder>sunspot</folder>
	<filename>20110307_000000_SDO_HMI_Ic_512.jpg</filename>
	<path>D:\kasi\Research\2020\2020_ObjectDetection\data\sunspot\20110307_000000_SDO_HMI_Ic_512.jpg</path>
	<source>
		<database>Unknown</database>
	</source>
	<size>
		<width>512</width>
		<height>512</height>
		<depth>3</depth>
	</size>
	<segmented>0</segmented>
	<object>
		<name>sunspot</name>
		<pose>Unspecified</pose>
		<truncated>0</truncated>
		<difficult>0</difficult>
		<bndbox>
			<xmin>117</xmin>
			<ymin>156</ymin>
			<xmax>183</xmax>
			<ymax>209</ymax>
		</bndbox>
	</object>
	<object>
		<name>sunspot</name>
		<pose>Unspecified</pose>
		<truncated>0</truncated>
		<difficult>0</difficult>
		<bndbox>
			<xmin>390</xmin>
			<ymin>123</ymin>
			<xmax>433</xmax>
			<ymax>158</ymax>
		</bndbox>
	</object>
	<object>
		<name>sunspot</name>
		<pose>Unspecified</pose>
		<truncated>0</truncated>
		<difficult>0</difficult>
		<bndbox>
			<xmin>265</xmin>
			<ymin>157</ymin>
			<xmax>300</xmax>
			<ymax>175</ymax>
		</bndbox>
	</object>
	<object>
		<name>sunspot</name>
		<pose>Unspecified</pose>
		<truncated>0</truncated>
		<difficult>0</difficult>
		<bndbox>
			<xmin>446</xmin>
			<ymin>296</ymin>
			<xmax>488</xmax>
			<ymax>340</ymax>
		</bndbox>
	</object>
</annotation>
