<annotation>
	<folder>prominence_1</folder>
	<filename>20110224_160008_SDO_AIA_304_512.jpg</filename>
	<path>D:\jhbaek\prominence_1\20110224_160008_SDO_AIA_304_512.jpg</path>
	<source>
		<database>Unknown</database>
	</source>
	<size>
		<width>512</width>
		<height>512</height>
		<depth>3</depth>
	</size>
	<segmented>0</segmented>
	<object>
		<name>prominence</name>
		<pose>Unspecified</pose>
		<truncated>0</truncated>
		<difficult>0</difficult>
		<bndbox>
			<xmin>25</xmin>
			<ymin>218</ymin>
			<xmax>69</xmax>
			<ymax>280</ymax>
		</bndbox>
	</object>
	<object>
		<name>prominence</name>
		<pose>Unspecified</pose>
		<truncated>0</truncated>
		<difficult>0</difficult>
		<bndbox>
			<xmin>318</xmin>
			<ymin>47</ymin>
			<xmax>375</xmax>
			<ymax>82</ymax>
		</bndbox>
	</object>
	<object>
		<name>prominence</name>
		<pose>Unspecified</pose>
		<truncated>0</truncated>
		<difficult>0</difficult>
		<bndbox>
			<xmin>377</xmin>
			<ymin>85</ymin>
			<xmax>441</xmax>
			<ymax>147</ymax>
		</bndbox>
	</object>
</annotation>
